tableauserverclient/__init__.py
tableauserverclient/config.py
tableauserverclient/datetime_helpers.py
tableauserverclient/exponential_backoff.py
tableauserverclient/filesys_helpers.py
tableauserverclient/namespace.py
tableauserverclient/py.typed
tableauserverclient/bin/_version.py
tableauserverclient/helpers/__init__.py
tableauserverclient/helpers/headers.py
tableauserverclient/helpers/logging.py
tableauserverclient/helpers/strings.py
tableauserverclient/models/__init__.py
tableauserverclient/models/column_item.py
tableauserverclient/models/connection_credentials.py
tableauserverclient/models/connection_item.py
tableauserverclient/models/custom_view_item.py
tableauserverclient/models/data_acceleration_report_item.py
tableauserverclient/models/data_alert_item.py
tableauserverclient/models/data_freshness_policy_item.py
tableauserverclient/models/database_item.py
tableauserverclient/models/datasource_item.py
tableauserverclient/models/dqw_item.py
tableauserverclient/models/exceptions.py
tableauserverclient/models/extract_item.py
tableauserverclient/models/favorites_item.py
tableauserverclient/models/fileupload_item.py
tableauserverclient/models/flow_item.py
tableauserverclient/models/flow_run_item.py
tableauserverclient/models/group_item.py
tableauserverclient/models/groupset_item.py
tableauserverclient/models/interval_item.py
tableauserverclient/models/job_item.py
tableauserverclient/models/linked_tasks_item.py
tableauserverclient/models/location_item.py
tableauserverclient/models/metric_item.py
tableauserverclient/models/pagination_item.py
tableauserverclient/models/permissions_item.py
tableauserverclient/models/project_item.py
tableauserverclient/models/property_decorators.py
tableauserverclient/models/reference_item.py
tableauserverclient/models/revision_item.py
tableauserverclient/models/schedule_item.py
tableauserverclient/models/server_info_item.py
tableauserverclient/models/site_item.py
tableauserverclient/models/subscription_item.py
tableauserverclient-0.38.dist-info/licenses/LICENSE
tableauserverclient-0.38.dist-info/licenses/LICENSE.versioneer
tableauserverclient-0.38.dist-info/METADATA
tableauserverclient-0.38.dist-info/WHEEL
tableauserverclient-0.38.dist-info/top_level.txt
tableauserverclient-0.38.dist-info/RECORD
