Metadata-Version: 2.4
Name: tableauserverclient
Version: 0.38
Summary: A Python module for working with the Tableau Server REST API.
Author-email: Tableau <github@tableau.com>
License: The MIT License (MIT)
Project-URL: repository, https://github.com/tableau/server-client-python
Classifier: Programming Language :: Python
Classifier: Programming Language :: Python :: 3
Classifier: Programming Language :: Python :: 3.9
Classifier: Programming Language :: Python :: 3.10
Classifier: Programming Language :: Python :: 3.11
Classifier: Programming Language :: Python :: 3.12
Classifier: Programming Language :: Python :: 3.13
Requires-Python: >=3.9
License-File: LICENSE
License-File: LICENSE.versioneer
Requires-Dist: defusedxml>=0.7.1
Requires-Dist: packaging>=23.1
Requires-Dist: requests>=2.32
Requires-Dist: urllib3<3,>=2.2.2
Requires-Dist: typing_extensions>=4.0
Provides-Extra: test
Requires-Dist: black==24.8; extra == "test"
Requires-Dist: build; extra == "test"
Requires-Dist: mypy==1.4; extra == "test"
Requires-Dist: pytest>=7.0; extra == "test"
Requires-Dist: pytest-cov; extra == "test"
Requires-Dist: pytest-subtests; extra == "test"
Requires-Dist: requests-mock<2.0,>=1.0; extra == "test"
Dynamic: license-file
